jarfetch/__init__.py
jarfetch/client.py
jarfetch/data_models.py
jarfetch/errors.py
jarfetch-0.2.1.dist-info/LICENSE
jarfetch-0.2.1.dist-info/METADATA
jarfetch-0.2.1.dist-info/WHEEL
jarfetch-0.2.1.dist-info/top_level.txt
jarfetch-0.2.1.dist-info/RECORD
