Metadata-Version: 2.1
Name: jarfetch
Version: 0.2.1
Summary: api wrapper for serverjars
Author-email: John Birdwell <j.c.birdwell@gmail.com>
License: MIT License
Project-URL: Repository, https://github.com/jcbirdwell/jarfetch
Keywords: jarfetch,serverjars,minecraft,jarfiles,server
Requires-Python: >=3.11
License-File: LICENSE
Requires-Dist: requests
Requires-Dist: tqdm
